{"cameraMode":{"drawMode":0,"name":"Shaded","section":"Shading Mode"},"sceneLighting":true,"audioPlay":false,"sceneViewState":{"showFog":true,"showMaterialUpdate":false,"showSkybox":true,"showFlares":true,"showImageEffects":true,"showParticleSystems":true},"in2DMode":false,"pivot":{"x":1.6881499290466309,"y":8.002546310424805,"z":28.246742248535158},"rotation":{"x":0.0024172074627131225,"y":-0.9943164587020874,"z":0.029360570013523103,"w":0.10405836254358292},"size":7.650521278381348,"orthographic":false}